ez_img_diff/__init__.py
ez_img_diff/api.py
ez_img_diff/cli.py
ez_img_diff-0.1.0.dist-info/LICENSE
ez_img_diff-0.1.0.dist-info/METADATA
ez_img_diff-0.1.0.dist-info/WHEEL
ez_img_diff-0.1.0.dist-info/entry_points.txt
ez_img_diff-0.1.0.dist-info/top_level.txt
ez_img_diff-0.1.0.dist-info/RECORD
