Metadata-Version: 2.1
Name: ez-img-diff
Version: 0.1.0
Summary: A tool for doing quick perceptual image difference analysis
Author: Kieran Wood
Author-email: kieran@canadiancoding.ca
Project-URL: API Docs, https://kieranwood.ca/ez_img_diff
Project-URL: Source, https://github.com/Descent098/ez-img-diff
Project-URL: Bug Report, https://github.com/Descent098/ez-img-diff/issues/new?assignees=Descent098&labels=bug&template=bug_report.md&title=%5BBUG%5D
Project-URL: Feature Request, https://github.com/Descent098/ez-img-diff/issues/new?labels=enhancement&template=feature_request.md&title=%5BFeature%5D
Project-URL: Roadmap, https://github.com/Descent098/ez-img-diff/projects
Classifier: Programming Language :: Python :: 3
Classifier: Operating System :: OS Independent
Classifier: Development Status :: 1 - Planning
License-File: LICENSE
Requires-Dist: docopt
Requires-Dist: scikit-image
Requires-Dist: imutils
Requires-Dist: opencv-python
Provides-Extra: dev
Requires-Dist: nox ; extra == 'dev'
Requires-Dist: pytest ; extra == 'dev'
Requires-Dist: mkdocs ; extra == 'dev'
